rayvens/__init__.py
rayvens/api.py
rayvens/rayvens_cli.py
rayvens/cli/__init__.py
rayvens/cli/build.py
rayvens/cli/delete.py
rayvens/cli/docker.py
rayvens/cli/file.py
rayvens/cli/java.py
rayvens/cli/kamel.py
rayvens/cli/kubernetes.py
rayvens/cli/rayvens_print.py
rayvens/cli/rayvens_setup.py
rayvens/cli/run.py
rayvens/cli/utils.py
rayvens/cli/version.py
rayvens/core/FileQueue.java
rayvens/core/FileQueueJson.java
rayvens/core/FileQueueName.java
rayvens/core/FileWatchQueue.java
rayvens/core/MetaEventQueue.java
rayvens/core/ProcessFile.java
rayvens/core/ProcessPath.java
rayvens/core/Queue.java
rayvens/core/__init__.py
rayvens/core/catalog.py
rayvens/core/catalog_utils.py
rayvens/core/common.py
rayvens/core/harness.py
rayvens/core/integration.py
rayvens/core/invocation.py
rayvens/core/kafka.py
rayvens/core/kamel.py
rayvens/core/kamel_backend.py
rayvens/core/kamel_utils.py
rayvens/core/kubernetes.py
rayvens/core/kubernetes_utils.py
rayvens/core/local.py
rayvens/core/mode.py
rayvens/core/name.py
rayvens/core/operator.py
rayvens/core/operator_kafka.py
rayvens/core/ray_serve.py
rayvens/core/utils.py
rayvens/core/verify.py
rayvens-0.7.0.data/scripts/rayvens
rayvens-0.7.0.data/scripts/rayvens-setup.sh
rayvens-0.7.0.data/scripts/rayvens_cli.py
rayvens-0.7.0.dist-info/AUTHORS
rayvens-0.7.0.dist-info/LICENSE.txt
rayvens-0.7.0.dist-info/METADATA
rayvens-0.7.0.dist-info/WHEEL
rayvens-0.7.0.dist-info/top_level.txt
rayvens-0.7.0.dist-info/RECORD
