Metadata-Version: 2.1
Name: rayvens
Version: 0.7.0
Summary: Rayvens augments Ray with events.
Home-page: https://github.com/project-codeflare/rayvens
Author: Rayvens authors
Author-email: tardieu@us.ibm.com, gheorghe-teod.bercea@ibm.com
License: Apache 2.0
Project-URL: Bug Reports, https://github.com/project-codeflare/rayvens/issues
Project-URL: Source, https://github.com/project-codeflare/rayvens
Keywords: ray events kubernetes
Platform: UNKNOWN
Classifier: Development Status :: 4 - Beta
Classifier: Intended Audience :: Developers
Classifier: License :: OSI Approved :: Apache Software License
Classifier: Programming Language :: Java
Classifier: Programming Language :: Python
Classifier: Programming Language :: Python :: 3
Classifier: Programming Language :: Python :: 3 :: Only
Classifier: Operating System :: OS Independent
Classifier: Topic :: System :: Distributed Computing
Requires-Python: >=3.6
Requires-Dist: confluent-kafka (>=1.6.1)
Requires-Dist: ray[default,k8s,serve] (>=1.3.0)
